pytdt/__init__.py
pytdt/pytdt.py
pytdt-0.6.2.dist-info/LICENSE.txt
pytdt-0.6.2.dist-info/METADATA
pytdt-0.6.2.dist-info/WHEEL
pytdt-0.6.2.dist-info/top_level.txt
pytdt-0.6.2.dist-info/RECORD
