Metadata-Version: 2.1
Name: pytdt
Version: 0.6.2
Summary: Tucker Davis Technologies tools
Home-page: UNKNOWN
Author: Logan Grado
Author-email: grado.logan@gmail.com
License: UNKNOWN
Platform: UNKNOWN
Requires-Dist: numpy
Requires-Dist: tabulate
Requires-Dist: regex
